pixiv_mcp/__init__.py
pixiv_mcp-0.1.0.dist-info/METADATA
pixiv_mcp-0.1.0.dist-info/WHEEL
pixiv_mcp-0.1.0.dist-info/entry_points.txt
pixiv_mcp-0.1.0.dist-info/RECORD
