Metadata-Version: 2.4
Name: pixiv-mcp
Version: 0.1.0
Summary: Add your description here
Author-email: Rikkawaii <2547083171@qq.com>
Requires-Python: >=3.11
Requires-Dist: beautifulsoup4>=4.13.4
Requires-Dist: mcp[cli]>=1.9.3
Requires-Dist: requests>=2.32.4
